rtl/digital_lock_controller.sv
module digital_lock_controller (
    input  logic clk,
    input  logic reset,
    input  logic enter,
    input  logic [3:0] digit,
    output logic unlock,
    output logic alarm
);

    logic [3:0] count;

    always_ff @(posedge clk or posedge reset) begin
        if (reset) begin
            count  <= 4'd0;
            unlock <= 1'b0;
            alarm  <= 1'b0;
        end
        else if (enter) begin
            if (digit == 4'd5) begin
                unlock <= 1'b1;
                alarm  <= 1'b0;
            end
            else begin
                unlock <= 1'b0;
                alarm  <= 1'b1;
            end
        end
    end

endmodule

tb/digital_lock_controller_gate_tb.sv
`timescale 1ns/1ps

module digital_lock_controller_tb;

    logic       clk;
    logic       reset;
    logic       enter;
    logic [3:0] digit;

    logic       unlock;
    logic       alarm;

    // Instantiate the Digital Lock Controller
    digital_lock_controller dut (
        .clk    (clk),
        .reset  (reset),
        .enter  (enter),
        .digit  (digit),
        .unlock (unlock),
        .alarm  (alarm)
    );

    // Clock generation: 10 ns period
    always #5 clk = ~clk;

    // Task to enter one digit
    task enter_digit(input logic [3:0] d);
        begin
            @(negedge clk);
            digit = d;
            enter = 1'b1;

            @(negedge clk);
            enter = 1'b0;
        end
    endtask

    initial begin
        $dumpfile("sim/digital_lock_gate.vcd");
        $dumpvars(0, digital_lock_controller_tb);

        clk   = 1'b0;
        reset = 1'b1;
        enter = 1'b0;
        digit = 4'd0;

        // Reset
        #20;
        reset = 1'b0;

        // Test 1: Correct digit/password input
        $display("TEST 1: Correct input");
        enter_digit(4'd5);

        #10;

        if (unlock == 1'b1)
            $display("TEST 1 PASSED: Unlock activated");
        else
            $display("TEST 1 FAILED: Unlock not activated");

        // Reset
        @(negedge clk);
        reset = 1'b1;
        @(negedge clk);
        reset = 1'b0;

        // Test 2: Wrong input
        $display("TEST 2: Wrong input");
        enter_digit(4'd7);

        #10;

        if (alarm == 1'b1)
            $display("TEST 2 PASSED: Alarm activated");
        else
            $display("TEST 2 FAILED: Alarm not activated");

        #20;

        $display("Simulation completed.");
        $finish;
    end

endmodule

waveforms/digital_lock_controller_2.vcd
$date
	Sat Oct  3 21:56:10 2026
$end
$version
	Icarus Verilog
$end
$timescale
	1ps
$end
$scope module digital_lock_controller_tb $end
$var wire 1 ! unlock $end
$var wire 1 " alarm $end
$var reg 1 # clk $end
$var reg 4 $ digit [3:0] $end
$var reg 1 % enter $end
$var reg 1 & reset $end
$scope module dut $end
$var wire 1 # clk $end
$var wire 4 ' digit [3:0] $end
$var wire 1 % enter $end
$var wire 1 & reset $end
$var reg 1 " alarm $end
$var reg 4 ( count [3:0] $end
$var reg 1 ! unlock $end
$upscope $end
$scope task enter_digit $end
$var reg 4 ) d [3:0] $end
$upscope $end
$upscope $end
$enddefinitions $end
$comment Show the parameter values. $end
$dumpall
$end
#0
$dumpvars
bx )
b0 (
b0 '
1&
0%
b0 $
0#
0"
0!
$end
#5000
1#
#10000
0#
#15000
1#
#20000
1%
b101 $
b101 '
0#
b101 )
0&
#25000
1!
1#
#30000
0%
0#
#35000
1#
#40000
0!
1&
0#
#45000
1#
#50000
b111 )
0&
0#
#55000
1#
#60000
1%
b111 $
b111 '
0#
#65000
1"
1#
#70000
0%
0#
